databases/__init__.py
databases/aiosql.py
databases/cursors.py
databases/mysql.py
databases/redisdb.py
databases/sqlite.py
py_dbclients-0.1.1.dist-info/LICENSE
py_dbclients-0.1.1.dist-info/METADATA
py_dbclients-0.1.1.dist-info/WHEEL
py_dbclients-0.1.1.dist-info/top_level.txt
py_dbclients-0.1.1.dist-info/RECORD
