Metadata-Version: 2.1
Name: py-dbclients
Version: 0.1.1
Summary: UNKNOWN
Home-page: UNKNOWN
License: UNKNOWN
Platform: UNKNOWN
License-File: LICENSE
Provides-Extra: aiomysql
Requires-Dist: aiomysql ; extra == 'aiomysql'
Provides-Extra: all
Requires-Dist: aiomysql ; extra == 'all'
Requires-Dist: pymysql ; extra == 'all'
Requires-Dist: redis[hiredis] ; extra == 'all'
Provides-Extra: pymysql
Requires-Dist: pymysql ; extra == 'pymysql'
Provides-Extra: redis
Requires-Dist: redis[hiredis] ; extra == 'redis'
